componentes/__init__.py
componentes/utils_carol.py
componentes/utils_python.py
componentes/utils_zendesk_api.py
componentes/utils_zendesk_scraping.py
componentes-0.2.6.dist-info/WHEEL
componentes-0.2.6.dist-info/METADATA
componentes-0.2.6.dist-info/RECORD
