Metadata-Version: 2.1
Name: componentes
Version: 0.2.6
Summary: Componetes de uso de teste
Author: Bruno S
Classifier: Programming Language :: Python :: 2
Classifier: Programming Language :: Python :: 2.7
Classifier: Programming Language :: Python :: 3
Classifier: Programming Language :: Python :: 3.10
Classifier: Programming Language :: Python :: 3.4
Classifier: Programming Language :: Python :: 3.5
Classifier: Programming Language :: Python :: 3.6
Classifier: Programming Language :: Python :: 3.7
Classifier: Programming Language :: Python :: 3.8
Classifier: Programming Language :: Python :: 3.9
Requires-Dist: nest_asyncio (>=1,<2)
Requires-Dist: pycarol (>=2.54.0,<3.0.0)
Requires-Dist: pymongo (>=4.1.0,<5.0.0)
Requires-Dist: requests (>=2.27.1,<3.0.0)
